adder.t.v
// Adder testbench
`timescale 1 ns / 1 ps
`include "adder.v"

module testFullAdder();
    reg a, b, carryin;
    wire sum, carryout;
    wire out1,out2,out3;

    //behavioralFullAdder adder (sum, carryout, a, b, carryin);
    structuralFullAdder adder (sum,carryout,a,b,carryin);

    initial begin
    $dumpfile("adder.vcd");
    $dumpvars();
    $display("A B Cin | S Cout | Expected Output");
    a=0;b=0;carryin=0; #1000 
    $display("%b  %b  %b |  %b  %b  | Sum 0, Carryout 0", a, b, carryin, sum, carryout);
    a=0;b=1;carryin=0; #1000
    $display("%b  %b  %b |  %b  %b  | Sum 1, Carryout 0", a, b, carryin, sum, carryout);
    a=1;b=0;carryin=0; #1000 
    $display("%b  %b  %b |  %b  %b  | Sum 1, Carryout 0", a, b, carryin, sum, carryout);
    a=1;b=1;carryin=0; #1000 
    $display("%b  %b  %b |  %b  %b  | Sum 0, Carryout 1", a, b, carryin, sum, carryout);
    a=0;b=0;carryin=1; #1000 
    $display("%b  %b  %b |  %b  %b  | Sum 1, Carryout 0", a, b, carryin, sum, carryout);
    a=0;b=1;carryin=1; #1000 
    $display("%b  %b  %b |  %b  %b  | Sum 0, Carryout 1", a, b, carryin, sum, carryout);
    a=1;b=0;carryin=1; #1000 
    $display("%b  %b  %b |  %b  %b  | Sum 0, Carryout 1", a, b, carryin, sum, carryout);
    a=1;b=1;carryin=1; #1000 
    $display("%b  %b  %b |  %b  %b  | Sum 1, Carryout 1", a, b, carryin, sum, carryout);
    $finish();
    end
endmodule

adder.v
// Adder circuit
`define AND and #50
`define OR or #50
`define NOT not #50
`define XOR xor #50

module behavioralFullAdder
(
    output sum, 
    output carryout,
    input a, 
    input b, 
    input carryin
);
    // Uses concatenation operator and built-in '+'
    assign {carryout, sum}=a+b+carryin;
endmodule


module structuralFullAdder
(
    output sum, 
    output carryout,
    input a, 
    input b, 
    input carryin
);
    wire out1,out2,out3;

    `XOR xor1(out1,a,b);
    `XOR xor2(sum,out1,carryin);

    `AND and1(out2,out1,carryin);
    `AND and2(out3,a,b);

    `OR or1(carryout,out2,out3);

endmodule

adder.vcd
$date
	Sat Sep 22 15:20:40 2018
$end
$version
	Icarus Verilog
$end
$timescale
	1ps
$end
$scope module behavioralFullAdder $end
$var wire 1 ! a $end
$var wire 1 " b $end
$var wire 1 # carryin $end
$var wire 1 $ sum $end
$var wire 1 % carryout $end
$upscope $end
$scope module testFullAdder $end
$var wire 1 & sum $end
$var wire 1 ' carryout $end
$var reg 1 ( a $end
$var reg 1 ) b $end
$var reg 1 * carryin $end
$scope module adder $end
$var wire 1 ( a $end
$var wire 1 ) b $end
$var wire 1 * carryin $end
$var wire 1 ' carryout $end
$var wire 1 + out1 $end
$var wire 1 , out2 $end
$var wire 1 - out3 $end
$var wire 1 & sum $end
$upscope $end
$upscope $end
$enddefinitions $end
#0
$dumpvars
x-
x,
x+
0*
0)
0(
x'
x&
x%
x$
z#
z"
z!
$end
#50000
0-
0,
0+
#100000
0'
0&
#1000000
1)
#1050000
1+
#1100000
1&
#2000000
0)
1(
#3000000
1)
#3050000
0+
1-
#3100000
0&
1'
#4000000
1*
0)
0(
#4050000
1&
0-
#4100000
0'
#5000000
1)
#5050000
1+
#5100000
0&
1,
#5150000
1'
#6000000
0)
1(
#7000000
1)
#7050000
0+
1-
#7100000
1&
0,
