decoder.t.v
// Decoder testbench
`timescale 1 ns / 1 ps
`include "decoder.v"

module testDecoder (); 

    reg address0, address1;
    reg enable;
    wire out0,out1,out2,out3;
    wire naddress0,naddress1;

    //behavioralDecoder decoder (out0,out1,out2,out3,addr0,addr1,enable);
    structuralDecoder decoder (out0,out1,out2,out3,address0,address1,enable); // Swap after testing
    //structuralDecoder decoder ( .out0(o0), .out1(o1), .out2(o2), .out3(o3), .address0(adress0), 

    initial begin
    $dumpfile("decoder.vcd");
    $dumpvars();
    $display("En A0 A1| O0 O1 O2 O3 | Expected Output");
    enable=0;address0=0;address1=0; #1000 
    $display("%b  %b  %b |  %b  %b  %b  %b | All false", enable, address0, address1, out0, out1, out2, out3);
    enable=0;address0=1;address1=0; #1000
    $display("%b  %b  %b |  %b  %b  %b  %b | All false", enable, address0, address1, out0, out1, out2, out3);
    enable=0;address0=0;address1=1; #1000 
    $display("%b  %b  %b |  %b  %b  %b  %b | All false", enable, address0, address1, out0, out1, out2, out3);
    enable=0;address0=1;address1=1; #1000 
    $display("%b  %b  %b |  %b  %b  %b  %b | All false", enable, address0, address1, out0, out1, out2, out3);
    enable=1;address0=0;address1=0; #1000 
    $display("%b  %b  %b |  %b  %b  %b  %b | O0 Only", enable, address0, address1, out0, out1, out2, out3);
    enable=1;address0=1;address1=0; #1000 
    $display("%b  %b  %b |  %b  %b  %b  %b | O1 Only", enable, address0, address1, out0, out1, out2, out3);
    enable=1;address0=0;address1=1; #1000 
    $display("%b  %b  %b |  %b  %b  %b  %b | O2 Only", enable, address0, address1, out0, out1, out2, out3);
    enable=1;address0=1;address1=1; #1000 
    $display("%b  %b  %b |  %b  %b  %b  %b | O3 Only", enable, address0, address1, out0, out1, out2, out3);
    $finish();
    end

endmodule

decoder.v
// Decoder circuit
`define AND and #50
`define OR or #50
`define NOT not #50

module behavioralDecoder
(
    output out0, out1, out2, out3,
    input address0, address1,
    input enable
);
    // Uses concatenation and shift operators
    assign {out3,out2,out1,out0}=enable<<{address1,address0};
endmodule


//module AND_AND (out,a0,a1,enable);
module AND_AND
(
    output out,
    input a0, a1,
    input enable
);

    wire not_out;

    `AND andgate1(not_out,a0,a1);
    `AND andgate2(out,enable,not_out);

endmodule


module structuralDecoder
(
    output out0, out1, out2, out3,
    input address0, address1,
    input enable
);
    wire naddress0, naddress1;

    `NOT address0inv(naddress0,address0);
    `NOT address1inv(naddress1,address1);

    AND_AND output0(out0,naddress0,naddress1,enable);
    AND_AND output1(out1,address0,naddress1,enable);
    AND_AND output2(out2,naddress0,address1,enable);
    AND_AND output3(out3,address0,address1,enable);

endmodule

decoder.vcd
$date
	Sat Sep 22 15:19:54 2018
$end
$version
	Icarus Verilog
$end
$timescale
	1ps
$end
$scope module behavioralDecoder $end
$var wire 1 ! address0 $end
$var wire 1 " address1 $end
$var wire 1 # enable $end
$var wire 1 $ out3 $end
$var wire 1 % out2 $end
$var wire 1 & out1 $end
$var wire 1 ' out0 $end
$upscope $end
$scope module testDecoder $end
$var wire 1 ( out3 $end
$var wire 1 ) out2 $end
$var wire 1 * out1 $end
$var wire 1 + out0 $end
$var reg 1 , address0 $end
$var reg 1 - address1 $end
$var reg 1 . enable $end
$scope module decoder $end
$var wire 1 , address0 $end
$var wire 1 - address1 $end
$var wire 1 . enable $end
$var wire 1 / naddress0 $end
$var wire 1 0 naddress1 $end
$var wire 1 ( out3 $end
$var wire 1 ) out2 $end
$var wire 1 * out1 $end
$var wire 1 + out0 $end
$scope module output0 $end
$var wire 1 / a0 $end
$var wire 1 0 a1 $end
$var wire 1 . enable $end
$var wire 1 1 not_out $end
$var wire 1 + out $end
$upscope $end
$scope module output1 $end
$var wire 1 , a0 $end
$var wire 1 0 a1 $end
$var wire 1 . enable $end
$var wire 1 2 not_out $end
$var wire 1 * out $end
$upscope $end
$scope module output2 $end
$var wire 1 / a0 $end
$var wire 1 - a1 $end
$var wire 1 . enable $end
$var wire 1 3 not_out $end
$var wire 1 ) out $end
$upscope $end
$scope module output3 $end
$var wire 1 , a0 $end
$var wire 1 - a1 $end
$var wire 1 . enable $end
$var wire 1 4 not_out $end
$var wire 1 ( out $end
$upscope $end
$upscope $end
$upscope $end
$enddefinitions $end
#0
$dumpvars
x4
x3
x2
x1
x0
x/
0.
0-
0,
x+
x*
x)
x(
x'
x&
x%
x$
z#
z"
z!
$end
#50000
10
1/
0(
04
0)
03
0*
02
0+
#100000
11
#1000000
1,
#1050000
0/
12
#1100000
01
#2000000
1-
0,
#2050000
00
1/
02
#2100000
13
#3000000
1,
#3050000
0/
14
#3100000
03
#4000000
0-
0,
1.
#4050000
10
1/
04
1(
#4100000
11
0(
#4150000
1+
#5000000
1,
#5050000
0/
12
#5100000
01
1*
#5150000
0+
#6000000
1-
0,
#6050000
00
1/
02
#6100000
13
0*
#6150000
1)
#7000000
1,
#7050000
0/
14
#7100000
03
1(
#7150000
0)
